reddit_rank_sort.pyx
setup.py
reddit_rank/__init__.py
reddit_rank/sorts.py
reddit_rank.egg-info/PKG-INFO
reddit_rank.egg-info/SOURCES.txt
reddit_rank.egg-info/dependency_links.txt
reddit_rank.egg-info/not-zip-safe
reddit_rank.egg-info/top_level.txt