Metadata-Version: 1.1
Name: reddit-rank
Version: 0.001
Summary: rebbit rank
Home-page: UNKNOWN
Author: UNKNOWN
Author-email: zsp007@gmail.com
License: UNKNOWN
Platform: UNKNOWN
Requires: pyrex
